ts103120/__init__.py
ts103120/catalog.py
ts103120/data/1.1.1/xsd/TS_103_280_v111.xsd
ts103120/data/1.1.1/xsd/ts_103120_Authorisation.xsd
ts103120/data/1.1.1/xsd/ts_103120_Common.xsd
ts103120/data/1.1.1/xsd/ts_103120_Core.xsd
ts103120/data/1.1.1/xsd/ts_103120_Document.xsd
ts103120/data/1.1.1/xsd/ts_103120_LITask.xsd
ts103120/data/1.1.1/xsd/ts_103120_Notification.xsd
ts103120/data/1.10.1/xsd/TS_103_280.xsd
ts103120/data/1.10.1/xsd/TS_103_280_v020601.xsd
ts103120/data/1.10.1/xsd/ts_103120_Authorisation.xsd
ts103120/data/1.10.1/xsd/ts_103120_Common.xsd
ts103120/data/1.10.1/xsd/ts_103120_Core.xsd
ts103120/data/1.10.1/xsd/ts_103120_Delivery.xsd
ts103120/data/1.10.1/xsd/ts_103120_Document.xsd
ts103120/data/1.10.1/xsd/ts_103120_Notification.xsd
ts103120/data/1.10.1/xsd/ts_103120_Task.xsd
ts103120/data/1.10.1/xsd/xmldsig-core-schema.xsd
ts103120/data/1.11.1/xsd/TS_103_280.xsd
ts103120/data/1.11.1/xsd/TS_103_280_v020601.xsd
ts103120/data/1.11.1/xsd/ts_103120_Authorisation.xsd
ts103120/data/1.11.1/xsd/ts_103120_Common.xsd
ts103120/data/1.11.1/xsd/ts_103120_Core.xsd
ts103120/data/1.11.1/xsd/ts_103120_Delivery.xsd
ts103120/data/1.11.1/xsd/ts_103120_Document.xsd
ts103120/data/1.11.1/xsd/ts_103120_Notification.xsd
ts103120/data/1.11.1/xsd/ts_103120_Task.xsd
ts103120/data/1.11.1/xsd/xmldsig-core-schema.xsd
ts103120/data/1.11.2/xsd/TS_103_280.xsd
ts103120/data/1.11.2/xsd/TS_103_280_v020601.xsd
ts103120/data/1.11.2/xsd/ts_103120_Authorisation.xsd
ts103120/data/1.11.2/xsd/ts_103120_Common.xsd
ts103120/data/1.11.2/xsd/ts_103120_Core.xsd
ts103120/data/1.11.2/xsd/ts_103120_Delivery.xsd
ts103120/data/1.11.2/xsd/ts_103120_Document.xsd
ts103120/data/1.11.2/xsd/ts_103120_Notification.xsd
ts103120/data/1.11.2/xsd/ts_103120_Task.xsd
ts103120/data/1.11.2/xsd/xmldsig-core-schema.xsd
ts103120/data/1.12.1/xsd/TS_103_280.xsd
ts103120/data/1.12.1/xsd/ts_103120_Authorisation.xsd
ts103120/data/1.12.1/xsd/ts_103120_Common.xsd
ts103120/data/1.12.1/xsd/ts_103120_Core.xsd
ts103120-0.1a4.dist-info/entry_points.txt
ts103120-0.1a4.dist-info/LICENSE
ts103120-0.1a4.dist-info/WHEEL
ts103120-0.1a4.dist-info/METADATA
ts103120-0.1a4.dist-info/RECORD
